cloner/__init__.py
cloner/__main__.py
cloner/__version__.py
cloner/banner.py
cloner/cli.py
cloner/clone_repos.py
cloner/cloner_process.py
cloner/cpu_config.py
cloner/obtain_repos.py
cloner/put_repos_in_queue.py
cloner/repository.py
cloner/split_exclude_repos.py
cloner/split_queue.py
wr_cloner-1.10.1.dist-info/licenses/LICENSE
wr_cloner-1.10.1.dist-info/METADATA
wr_cloner-1.10.1.dist-info/WHEEL
wr_cloner-1.10.1.dist-info/entry_points.txt
wr_cloner-1.10.1.dist-info/top_level.txt
wr_cloner-1.10.1.dist-info/RECORD
