Metadata-Version: 2.4
Name: wr-cloner
Version: 1.10.1
Summary: A tool to clone efficiently all the repos in an organization
Author: w0rmr1d3r
License: MIT
Project-URL: Homepage, https://github.com/w0rmr1d3r/cloner
Project-URL: Repository, https://github.com/w0rmr1d3r/cloner
Project-URL: Bug Tracker, https://github.com/w0rmr1d3r/cloner/issues
Project-URL: Documentation, https://github.com/w0rmr1d3r/cloner
Project-URL: Changelog, https://github.com/w0rmr1d3r/cloner/releases
Project-URL: Funding, https://github.com/sponsors/w0rmr1d3r
Keywords: github,python,git,clone,organization,multiprocessing,multithreading,python3
Classifier: Development Status :: 5 - Production/Stable
Classifier: Environment :: Console
Classifier: Intended Audience :: Developers
Classifier: Intended Audience :: Information Technology
Classifier: Intended Audience :: System Administrators
Classifier: License :: OSI Approved :: MIT License
Classifier: Programming Language :: Python
Classifier: Programming Language :: Python :: 3
Classifier: Programming Language :: Python :: 3.9
Classifier: Programming Language :: Python :: 3.10
Classifier: Programming Language :: Python :: 3.11
Classifier: Programming Language :: Python :: 3.12
Classifier: Programming Language :: Python :: 3.13
Classifier: Topic :: Security
Classifier: Topic :: Software Development :: Version Control
Classifier: Topic :: Software Development :: Version Control :: Git
Classifier: Topic :: System
Requires-Python: >=3.9.0
License-File: LICENSE
Requires-Dist: click>=8.0.3
Requires-Dist: requests>=2.27.1
Provides-Extra: dev
Requires-Dist: coverage>=6.3.2; extra == "dev"
Requires-Dist: faker>=12.0.1; extra == "dev"
Requires-Dist: pip-tools>=6.5.0; extra == "dev"
Requires-Dist: pytest>=6.2.5; extra == "dev"
Requires-Dist: responses>=0.20.0; extra == "dev"
Requires-Dist: ruff==0.9.2; extra == "dev"
Provides-Extra: build
Requires-Dist: build~=1.0; extra == "build"
Dynamic: license-file
